invoker_terminal/__init__.py
invoker_terminal/__main__.py
invoker_terminal/ast_check.py
invoker_terminal/base.py
invoker_terminal/cli.py
invoker_terminal/client.py
invoker_terminal/constants.py
invoker_terminal/core.py
invoker_terminal/server.py
invoker_terminal/utils.py
invoker_terminal-0.1.0.dist-info/LICENSE
invoker_terminal-0.1.0.dist-info/METADATA
invoker_terminal-0.1.0.dist-info/WHEEL
invoker_terminal-0.1.0.dist-info/entry_points.txt
invoker_terminal-0.1.0.dist-info/top_level.txt
invoker_terminal-0.1.0.dist-info/RECORD
