Metadata-Version: 2.1
Name: invoker-terminal
Version: 0.1.0
Summary: Awesome invoker_terminal created by m00dy
Home-page: https://github.com/m00dy/invoker-terminal/
Author: m00dy
License-File: LICENSE
Requires-Dist: docker
Requires-Dist: termcolor
Requires-Dist: solana
Requires-Dist: anchorpy
Requires-Dist: solders
Requires-Dist: pynacl
Requires-Dist: base58
Requires-Dist: aiohttp
Requires-Dist: SQLAlchemy
Requires-Dist: pick
Requires-Dist: aiodocker
Provides-Extra: test
Requires-Dist: pytest ; extra == 'test'
Requires-Dist: coverage ; extra == 'test'
Requires-Dist: flake8 ; extra == 'test'
Requires-Dist: black ; extra == 'test'
Requires-Dist: isort ; extra == 'test'
Requires-Dist: pytest-cov ; extra == 'test'
Requires-Dist: mypy ; extra == 'test'
Requires-Dist: gitchangelog ; extra == 'test'
Requires-Dist: mkdocs ; extra == 'test'
